{"type":"FeatureCollection","features":[{"type":"Feature","properties":{"marker-color":"#ff00c8","marker-size":"medium","marker-symbol":"parking","Name":"Pin Yo","Descriptin ":"Wassssuuuuuuuuuup my dude"},"geometry":{"type":"Point","coordinates":[135,66.65297740055279]}},{"type":"Feature","geometry":{"type":"Point","coordinates":[161.12585506822182,42.42858866072658]},"properties":{}},{"type":"Feature","geometry":{"type":"Point","coordinates":[103.31395039965066,12.069916765935735]},"properties":{}},{"type":"Feature","geometry":{"type":"Point","coordinates":[-72.58271831575203,59.57877242533943]},"properties":{}},{"type":"Feature","geometry":{"type":"Point","coordinates":[87.67180611454688,75.69218527000089]},"properties":{}},{"type":"Feature","geometry":{"type":"Point","coordinates":[-111.75587383501714,31.604564696854208]},"properties":{}},{"type":"Feature","geometry":{"type":"Point","coordinates":[-170.97466269347564,61.73083640527205]},"properties":{}},{"type":"Feature","geometry":{"type":"Point","coordinates":[-29.306114368351814,-2.3529456518515257]},"properties":{}},{"type":"Feature","geometry":{"type":"Point","coordinates":[-57.387805091204356,-10.717460330625643]},"properties":{}},{"type":"Feature","geometry":{"type":"Point","coordinates":[69.71252578335408,-56.56283283809274]},"properties":{}},{"type":"Feature","geometry":{"type":"Point","coordinates":[-172.6042439354112,32.88739119043335]},"properties":{}},{"type":"Feature","geometry":{"type":"Point","coordinates":[-69.44673035422657,66.2359981405556]},"properties":{}},{"type":"Feature","geometry":{"type":"Point","coordinates":[-46.430248003199914,-33.84255103964871]},"properties":{}},{"type":"Feature","geometry":{"type":"Point","coordinates":[127.71785817497845,-28.31621445337547]},"properties":{}},{"type":"Feature","geometry":{"type":"Point","coordinates":[70.68514452379334,4.24384239566836]},"properties":{}},{"type":"Feature","geometry":{"type":"Point","coordinates":[108.03442875972196,-62.44658972708543]},"properties":{}},{"type":"Feature","geometry":{"type":"Point","coordinates":[120.06650067034143,25.45839796175954]},"properties":{}}]}